jolly_roger/__init__.py
jolly_roger/_version.py
jolly_roger/_version.pyi
jolly_roger/baselines.py
jolly_roger/delays.py
jolly_roger/flagger.py
jolly_roger/hour_angles.py
jolly_roger/logging.py
jolly_roger/plots.py
jolly_roger/py.typed
jolly_roger/tractor.py
jolly_roger/utils.py
jolly_roger/uvws.py
jolly_roger/wrap.py
jolly_roger-0.7.0.dist-info/METADATA
jolly_roger-0.7.0.dist-info/WHEEL
jolly_roger-0.7.0.dist-info/entry_points.txt
jolly_roger-0.7.0.dist-info/licenses/LICENSE
jolly_roger-0.7.0.dist-info/RECORD
