Metadata-Version: 2.4
Name: jolly-roger
Version: 0.7.0
Summary: The pirate flagger
Project-URL: Homepage, https://github.com/flint-crew/jolly-roger
Project-URL: Bug Tracker, https://github.com/flint-crew/jolly-roger/issues
Project-URL: Discussions, https://github.com/flint-crew/jolly-roger/discussions
Project-URL: Changelog, https://github.com/flint-crew/jolly-roger/releases
Author-email: Alec Thomson <alec.thomson@csiro.au>
License-Expression: BSD-3-Clause
License-File: LICENSE
Classifier: Development Status :: 1 - Planning
Classifier: Intended Audience :: Developers
Classifier: Intended Audience :: Science/Research
Classifier: Operating System :: OS Independent
Classifier: Programming Language :: Python
Classifier: Programming Language :: Python :: 3
Classifier: Programming Language :: Python :: 3 :: Only
Classifier: Programming Language :: Python :: 3.11
Classifier: Programming Language :: Python :: 3.12
Classifier: Programming Language :: Python :: 3.13
Classifier: Topic :: Scientific/Engineering
Classifier: Typing :: Typed
Requires-Python: >=3.11
Requires-Dist: astropy
Requires-Dist: dask-ms
Requires-Dist: matplotlib
Requires-Dist: numpy>=2.0.0
Requires-Dist: python-casacore>=3.6.0
Requires-Dist: tqdm
